LICENSE
MANIFEST.in
README.md
requirements.txt
setup.py
aiosock/__init__.py
aiosock.egg-info/PKG-INFO
aiosock.egg-info/SOURCES.txt
aiosock.egg-info/dependency_links.txt
aiosock.egg-info/requires.txt
aiosock.egg-info/top_level.txt