Metadata-Version: 2.1
Name: aiosock
Version: 1.0.6
Summary: Multiprocess communication sockets for asyncio
Home-page: https://github.com/bowen-xu/aiosock
Author: Bowen XU
Author-email: xubowen@pku.edu.cn
License: MIT
Keywords: asyncio,multiprocess,socket
Classifier: Development Status :: 4 - Beta
Classifier: Intended Audience :: Developers
Classifier: License :: OSI Approved :: MIT License
Classifier: Natural Language :: English
Classifier: Natural Language :: Chinese (Simplified)
Classifier: Programming Language :: Python :: 3.7
Classifier: Programming Language :: Python :: 3.8
Classifier: Programming Language :: Python :: 3.9
Classifier: Programming Language :: Python :: 3.10
Classifier: Programming Language :: Python :: 3.11
Classifier: Programming Language :: Python :: Implementation :: CPython
Classifier: Programming Language :: Python :: Implementation :: PyPy
Requires-Python: >=3.7.0
License-File: LICENSE
